manychat_block/__init__.py
manychat_block-0.1.1.dist-info/LICENSE.md
manychat_block-0.1.1.dist-info/WHEEL
manychat_block-0.1.1.dist-info/METADATA
manychat_block-0.1.1.dist-info/RECORD
