Metadata-Version: 2.1
Name: manychat-block
Version: 0.1.1
Summary: 
License: ISC
Author: naspa c
Author-email: naspa612@gmail.com
Requires-Python: >=3.6,<4.0
Classifier: License :: OSI Approved
Classifier: Programming Language :: Python :: 3
Classifier: Programming Language :: Python :: 3.6
Classifier: Programming Language :: Python :: 3.7
Classifier: Programming Language :: Python :: 3.8
Requires-Dist: literal (>=1.0.0,<2.0.0)
Requires-Dist: typing-extensions (>=3.7.4,<4.0.0)
